[
    {
      "id": 0,
      "name": "Star Wars Jedi: Fallen Order",
      "verticalsrc": "/assets/jedifallenordervertical.jpeg",
      "horizontalsrc": "/assets/fallenorderhorizontal.jpg",
      "genre": "Action",
      "publisher": "Electronic Arts",
      "developer": "Respawn Entertainment",
      "liked": false,
      "releaseDate": "11/15/2019",
      "price": 59.99
    },
    {
      "id": 1,
      "name": "Bloodborne",
      "verticalsrc": "/assets/Bloodborne-cover.jpeg",
      "horizontalsrc": "/assets/bloodbornehorizontal.jpg",
      "genre": "RPG",
      "publisher": "Sony Computer Entertainment",
      "developer": "FromSoftware",
      "liked": false,
      "releaseDate": "03/24/2015",
      "price": 39.99
    },
    {
      "id": 2,
      "name": "Baldur's Gate 3",
      "verticalsrc": "/assets/baldursgate.jpeg",
      "horizontalsrc": "/assets/baldursgate3horizontal.jpg",
      "genre": "RPG",
      "publisher": "Larian Studios",
      "developer": "Larian Studios",
      "liked": false,
      "releaseDate": "10/06/2020",
      "price": 49.99
    },
    {
      "id": 3,
      "name": "The Elder Scrolls V: Skyrim",
      "verticalsrc": "/assets/skyrim-cover.jpeg",
      "horizontalsrc": "/assets/skyrimhorizontal.jpg",
      "genre": "RPG",
      "publisher": "Bethesda Softworks",
      "developer": "Bethesda Game Studios",
      "liked": false,
      "releaseDate": "11/11/2011",
      "price": 19.99
    },
    {
      "id": 4,
      "name": "Elden Ring",
      "verticalsrc": "/assets/eldenring-cover.jpeg",
      "horizontalsrc": "/assets/eldenringhorizontal.jpg",
      "genre": "RPG",
      "publisher": "Bandai Namco Entertainment",
      "developer": "FromSoftware",
      "liked": false,
      "releaseDate": "02/25/2022",
      "price": 69.99
    },
    {
      "id": 5,
      "name": "The Witcher 3: Wild Hunt",
      "verticalsrc": "/assets/thewitcher3.jpeg",
      "horizontalsrc": "/assets/thewitcher3horizontal.jpg",
      "genre": "RPG",
      "publisher": "CD Projekt",
      "developer": "CD Projekt Red",
      "liked": false,
      "releaseDate": "05/19/2015",
      "price": 29.99
    },
    {
      "id": 6,
      "name": "Cyberpunk 2077",
      "verticalsrc": "/assets/Cyberpunk2077.jpeg",
      "horizontalsrc": "/assets/cyberpunk2077horizontal",
      "genre": "RPG",
      "publisher": "CD Projekt",
      "developer": "CD Projekt Red",
      "liked": false,
      "releaseDate": "12/10/2020",
      "price": 49.99
    },
    {
      "id": 7,
      "name": "Star Wars Battlefront II",
      "verticalsrc": "/assets/battlefront2.jpeg",
      "horizontalsrc": "/assets/battlefront2horizontal.png",
      "genre": "Action",
      "publisher": "Electronic Arts",
      "developer": "DICE",
      "liked": false,
      "releaseDate": "11/17/2017",
      "price": 19.99
    },
    {
      "id": 8,
      "name": "FIFA 24",
      "verticalsrc": "/assets/fifa24.jpeg",
      "horizontalsrc": "/assets/fifa24horizontal.jpeg",
      "genre": "Sports",
      "publisher": "Electronic Arts",
      "developer": "EA Sports",
      "liked": false,
      "releaseDate": "09/29/2023",
      "price": 59.99
    },
    {
      "id": 9,
      "name": "FIFA 23",
      "verticalsrc": "/assets/fifa23.jpeg",
      "horizontalsrc": "/assets/fifa23horizontal.wbep",
      "genre": "Sports",
      "publisher": "Electronic Arts",
      "developer": "EA Sports",
      "liked": false,
      "releaseDate": "09/30/2022",
      "price": 49.99
    },
    {
      "id": 10,
      "name": "FIFA 22",
      "verticalsrc": "/assets/fifa22.jpeg",
      "horizontalsrc": "/assets/fifa22horizontal.jpg",
      "genre": "Sports",
      "publisher": "Electronic Arts",
      "developer": "EA Sports",
      "liked": false,
      "releaseDate": "10/01/2021",
      "price": 39.99
    },
    {
      "id": 11,
      "name": "Star Wars Jedi: Survivor",
      "verticalsrc": "/assets/jedisurvivorvertical.jpeg",
      "horizontalsrc": "/assets/jedisurvivorhorizontal.jpg",
      "genre": "Action",
      "publisher": "Electronic Arts",
      "developer": "Respawn Entertainment",
      "liked": false,
      "releaseDate": "04/28/2023",
      "price": 69.99
    },
    {
      "id": 12,
      "name": "Resident Evil 2 Remake",
      "verticalsrc": "/assets/residentevil2remake.jpeg",
      "horizontalsrc": "/assets/residentevil2horizontal.png",
      "genre": "Horror, Action",
      "publisher": "Capcom",
      "developer": "Capcom",
      "liked": false,
      "releaseDate": "01/25/2019",
      "price": 39.99
    },
    {
      "id": 13,
      "name": "Resident Evil 4 Remake",
      "verticalsrc": "/assets/residentevil4remake.jpeg",
      "horizontalsrc": "/assets/residentevil4horizontal.jpg",
      "genre": "Horror, Action",
      "publisher": "Capcom",
      "developer": "Capcom",
      "liked": false,
      "releaseDate": "03/24/2023",
      "price": 49.99
    },
    {
      "id": 14,
      "name": "Resident Evil Village",
      "verticalsrc": "/assets/residentevilvillage.jpeg",
      "horizontalsrc": "/assets/residentevilvillagehorizontal.png",
      "genre": "Horror, Action",
      "publisher": "Capcom",
      "developer": "Capcom",
      "liked": false,
      "releaseDate": "05/07/2021",
      "price": 59.99
    },
    {
      "id": 15,
      "name": "Control",
      "verticalsrc": "/assets/controlvertical.jpg",
      "horizontalsrc": "/assets/controlhorizontal.png",
      "genre": "Action",
      "publisher": "505 Games",
      "developer": "Remedy Entertainment",
      "liked": false,
      "releaseDate": "08/27/2019",
      "price": 29.99
    },
    {
      "id": 16,
      "name": "Diablo IV",
      "verticalsrc": "/assets/diabloIVvertical.webp",
      "horizontalsrc": "/assets/diabloIVhorizontal.avif",
      "genre": "RPG",
      "publisher": "Blizzard Entertainment",
      "developer": "Blizzard Entertainment",
      "liked": false,
      "releaseDate": "05/06/2023",
      "price": 69.99
    },
    {
      "id": 17,
      "name": "Sekiro: Shadows Die Twice",
      "verticalsrc": "/assets/sekiroVertical.png",
      "horizontalsrc": "/assets/sekiroHorizontal.webp",
      "genre": "Action-Adventure",
      "publisher": "Activision",
      "developer": "FromSoftware",
      "liked": false,
      "releaseDate": "22/03/2019",
      "price": 59.99
    },
    {
      "id": 18,
      "name": "God of War",
      "verticalsrc": "/assets/godofwarvertical.jpg",
      "horizontalsrc": "/assets/godofwarhorizontal.jpeg",
      "genre": "Action-Adventure",
      "publisher": "Sony Interactive Entertainment",
      "developer": "Santa Monica Studio",
      "liked": false,
      "releaseDate": "04/20/2018",
      "price": 49.99
    }
  ]
  